setup.py
sixtracktools/__init__.py
sixtracktools/sixbin.py
sixtracktools/sixdump.py
sixtracktools/sixinput.py
sixtracktools/sixtrack_slicing_table.py
sixtracktools/xline_generation.py
sixtracktools.egg-info/PKG-INFO
sixtracktools.egg-info/SOURCES.txt
sixtracktools.egg-info/dependency_links.txt
sixtracktools.egg-info/requires.txt
sixtracktools.egg-info/top_level.txt